INOKrypt/INOKrypt.py
INOKrypt/__init__.py
INOKrypt-0.1.1.dist-info/LICENSE
INOKrypt-0.1.1.dist-info/METADATA
INOKrypt-0.1.1.dist-info/WHEEL
INOKrypt-0.1.1.dist-info/top_level.txt
INOKrypt-0.1.1.dist-info/RECORD
